Metadata-Version: 2.1
Name: superanime
Version: 1.0.3
Summary: The best package in Python to get anime information and anime gifs!
Home-page: https://github.com/MoonlightGroup/anime.py
Author: Noraa08
Author-email: rafael.noraa08@gmail.com
